PharmaPy/Calibration.py
PharmaPy/CheckModule.py
PharmaPy/Commons.py
PharmaPy/Connections.py
PharmaPy/Containers.py
PharmaPy/Crystallizers.py
PharmaPy/Distillation.py
PharmaPy/Drying_Model.py
PharmaPy/DynamicExtraction.py
PharmaPy/Errors.py
PharmaPy/Evaporators.py
PharmaPy/Extractors.py
PharmaPy/Gaussians.py
PharmaPy/Interpolation.py
PharmaPy/Kinetics.py
PharmaPy/LevMarq.py
PharmaPy/MetaModeler.py
PharmaPy/MixedPhases.py
PharmaPy/NameAnalysis.py
PharmaPy/ParamEstim.py
PharmaPy/Phases.py
PharmaPy/Plotting.py
PharmaPy/ProcessControl.py
PharmaPy/Reactors.py
PharmaPy/Results.py
PharmaPy/SimExec.py
PharmaPy/SolidLiquidSep.py
PharmaPy/StatsModule.py
PharmaPy/Streams.py
PharmaPy/ThermoModule.py
PharmaPy/ThreePhaseSettler.py
PharmaPy/Utilities.py
PharmaPy/__init__.py
PharmaPy/animate_profiles.py
PharmaPy/general_interpolation.py
PharmaPy/jac_module.py
data/minimum_modeling_objects.json
PharmaTwin-0.0.1.dist-info/LICENSE.md
PharmaTwin-0.0.1.dist-info/METADATA
PharmaTwin-0.0.1.dist-info/WHEEL
PharmaTwin-0.0.1.dist-info/top_level.txt
PharmaTwin-0.0.1.dist-info/RECORD
