Metadata-Version: 2.1
Name: PharmaTwin
Version: 0.0.1
Home-page: https://github.com/CryPTSys/PharmaPy
Author: Daniel Casas-Orozco
Author-email: dcasasor@purdue.edu
License: LICENSE.md
License-File: LICENSE.md
Requires-Dist: pyomo
Requires-Dist: coverage
Requires-Dist: numpy
Requires-Dist: scipy
Requires-Dist: pandas
Requires-Dist: assimulo
